chatgpt_repl/__init__.py
chatgpt_repl/__main__.py
chatgpt_repl/cli.py
chatgpt_repl-0.1.0.dist-info/METADATA
chatgpt_repl-0.1.0.dist-info/WHEEL
chatgpt_repl-0.1.0.dist-info/entry_points.txt
chatgpt_repl-0.1.0.dist-info/top_level.txt
chatgpt_repl-0.1.0.dist-info/RECORD
